mysql_shell/__init__.py
mysql_shell/builders/__init__.py
mysql_shell/builders/authorization/__init__.py
mysql_shell/builders/authorization/base.py
mysql_shell/builders/authorization/charm.py
mysql_shell/builders/locking/__init__.py
mysql_shell/builders/locking/base.py
mysql_shell/builders/locking/charm.py
mysql_shell/builders/logging/__init__.py
mysql_shell/builders/logging/base.py
mysql_shell/builders/logging/charm.py
mysql_shell/builders/quoting.py
mysql_shell/clients/__init__.py
mysql_shell/clients/cluster.py
mysql_shell/clients/instance.py
mysql_shell/executors/__init__.py
mysql_shell/executors/base.py
mysql_shell/executors/errors/__init__.py
mysql_shell/executors/errors/runtime.py
mysql_shell/executors/local.py
mysql_shell/models/__init__.py
mysql_shell/models/account.py
mysql_shell/models/cluster.py
mysql_shell/models/connection.py
mysql_shell/models/instance.py
mysql_shell/models/statement.py
mysql_shell_client-0.6.1.dist-info/METADATA
mysql_shell_client-0.6.1.dist-info/WHEEL
mysql_shell_client-0.6.1.dist-info/licenses/LICENSE
mysql_shell_client-0.6.1.dist-info/RECORD
