Metadata-Version: 2.4
Name: mysql-shell-client
Version: 0.6.1
Summary: Python client for MySQL Shell
License-Expression: Apache-2.0
License-File: LICENSE
Author: Sinclert Perez
Author-email: sinclert.perez@canonical.com
Maintainer: Canonical Data Platform
Maintainer-email: data-platform@lists.launchpad.net
Requires-Python: >=3.10
Classifier: Programming Language :: Python :: 3
Classifier: Programming Language :: Python :: 3.10
Classifier: Programming Language :: Python :: 3.11
Classifier: Programming Language :: Python :: 3.12
Classifier: Programming Language :: Python :: 3.13
Classifier: Programming Language :: Python :: 3.14
Provides-Extra: format
Provides-Extra: lint
Provides-Extra: test
Requires-Dist: codespell (>=2.3,<3.0) ; extra == "lint"
Requires-Dist: coverage (>=7.6,<8.0) ; extra == "test"
Requires-Dist: pytest (>=8.3,<9.0) ; extra == "test"
Requires-Dist: ruff (>=0.9,<1.0) ; extra == "format"
Requires-Dist: ruff (>=0.9,<1.0) ; extra == "lint"
Project-URL: Changelog, https://github.com/canonical/mysql-shell-client/blob/main/CHANGELOG.md
Project-URL: Homepage, https://github.com/canonical/mysql-shell-client
Project-URL: Issues, https://github.com/canonical/mysql-shell-client/issues
